alt_time_utils/__init__.py
alt_time_utils/constants.py
alt_time_utils/core.py
alt_time_utils/py.typed
alt_time_utils-0.1.1.dist-info/licenses/LICENSE
alt_time_utils-0.1.1.dist-info/METADATA
alt_time_utils-0.1.1.dist-info/WHEEL
alt_time_utils-0.1.1.dist-info/top_level.txt
alt_time_utils-0.1.1.dist-info/RECORD
