Metadata-Version: 2.4
Name: ALT-time-utils
Version: 0.1.1
Summary: A collection of time-related utility functions for Python
Author-email: Avi Layani <alayani@redhat.com>
Maintainer-email: Avi Layani <alayani@redhat.com>
License-Expression: MIT
Project-URL: Homepage, https://github.com/Avilir/time_utils
Project-URL: Repository, https://github.com/Avilir/time_utils
Project-URL: Bug Tracker, https://github.com/Avilir/time_utils/issues
Keywords: time,datetime,timezone,utilities,formatting
Classifier: Development Status :: 3 - Alpha
Classifier: Intended Audience :: Developers
Classifier: Operating System :: OS Independent
Classifier: Programming Language :: Python :: 3
Classifier: Programming Language :: Python :: 3.8
Classifier: Programming Language :: Python :: 3.9
Classifier: Programming Language :: Python :: 3.10
Classifier: Programming Language :: Python :: 3.11
Classifier: Programming Language :: Python :: 3.12
Classifier: Topic :: Software Development :: Libraries :: Python Modules
Classifier: Topic :: Utilities
Classifier: Typing :: Typed
Requires-Python: >=3.8
License-File: LICENSE
Provides-Extra: dev
Requires-Dist: pytest>=7.0.0; extra == "dev"
Requires-Dist: pytest-cov>=4.0.0; extra == "dev"
Requires-Dist: mypy>=1.0.0; extra == "dev"
Requires-Dist: ruff>=0.1.0; extra == "dev"
Requires-Dist: black>=23.0.0; extra == "dev"
Requires-Dist: pre-commit>=3.0.0; extra == "dev"
Requires-Dist: build>=0.10.0; extra == "dev"
Requires-Dist: twine>=4.0.0; extra == "dev"
Dynamic: license-file
